openlrw/__init__.py
openlrw/client.py
openlrw/exceptions.py
openlrw/oneroster.py
openlrw/routes.py
openlrw-1.0.5.dist-info/LICENSE
openlrw-1.0.5.dist-info/METADATA
openlrw-1.0.5.dist-info/WHEEL
openlrw-1.0.5.dist-info/top_level.txt
openlrw-1.0.5.dist-info/RECORD
