Metadata-Version: 2.1
Name: openlrw
Version: 1.0.5
Summary: Client library for Apereo OpenLRW API
Home-page: https://github.com/Apereo-Learning-Analytics-Initiative/OpenLRW-python-api-client
Author: Xavier Chopin
Author-email: bonjour@xavierchop.in
License: ECL-2.0
Keywords: apereo openlrw api client
Platform: UNKNOWN
Classifier: Intended Audience :: Developers
Classifier: Intended Audience :: Information Technology
Classifier: Intended Audience :: Education
Classifier: Natural Language :: English
Classifier: Programming Language :: Python
Classifier: Programming Language :: Python :: 2.7
Classifier: Programming Language :: Python :: 3.4
Classifier: Programming Language :: Python :: 3.5
Classifier: Programming Language :: Python :: 3.6
Requires-Dist: requests
